{
	"entries":[
		{
			"id":"first_meeting",
			"priority":100,
			"conditions": ["not_met:bruja"],
			"effects": ["met:bruja"],
			"nodes":{
				"start":{
					"text": "Oh! Finally! I've been triying so long to wake you up.",
					"choices": [
						{
							"text": "Who are you?",
							"next": "who_bruja"
						},
						{
							"text": "Who am I?",
							"next": "who_player"
						},
						{
							"text": "...",
							"next": "get_to_work"
						}
					]
				},
				"who_bruja":{
					"text": "Don't be silly. We have wasted enough time as is.",
					"next": "get_to_work"
				},
				"who_player":{
					"text": "Did the petrification make you loose your memory? You are my familiar! A cute, little helper for when i need to make potions.",
					"next": "get_to_work"
				},
				"get_to_work":{
					"text": "Well, lets get to work, come on now! Try moving using the 'wasd' keys!",
					"effects":["activate_quest:identification_tutorial"],
					"end": true
				}
			}
		},
		{
			"id":"default",
			"priority":0,
			"conditions": [],
			"nodes":{
				"0":{
					"text": "I wonder how the weather will be tomorrow. ",
					"end":true
				},
				"1":{
					"text": "Do you want potato salad?",
					"end": true
				}
			}
		}
	]
}
